hkopenai/hk_transportation_mcp_server/__init__.py
hkopenai/hk_transportation_mcp_server/__main__.py
hkopenai/hk_transportation_mcp_server/server.py
hkopenai/hk_transportation_mcp_server/tools/__init__.py
hkopenai/hk_transportation_mcp_server/tools/bus_kmb.py
hkopenai/hk_transportation_mcp_server/tools/land_custom_wait_time.py
hkopenai/hk_transportation_mcp_server/tools/passenger_traffic.py
iflow_mcp_hk_transportation_mcp_server-0.3.0.dist-info/licenses/LICENSE
iflow_mcp_hk_transportation_mcp_server-0.3.0.dist-info/METADATA
iflow_mcp_hk_transportation_mcp_server-0.3.0.dist-info/WHEEL
iflow_mcp_hk_transportation_mcp_server-0.3.0.dist-info/entry_points.txt
iflow_mcp_hk_transportation_mcp_server-0.3.0.dist-info/top_level.txt
iflow_mcp_hk_transportation_mcp_server-0.3.0.dist-info/RECORD
